pysdl2/__init__.py
python_sdl2-0.0.2.dist-info/LICENSE
python_sdl2-0.0.2.dist-info/METADATA
python_sdl2-0.0.2.dist-info/WHEEL
python_sdl2-0.0.2.dist-info/RECORD
