Metadata-Version: 2.1
Name: python-sdl2
Version: 0.0.2
Summary: python wrapper for SDL2
License: MIT
Author: luzhixing12345
Author-email: luzhixing12345@163.com
Requires-Python: >=3.7,<4.0
Classifier: License :: OSI Approved :: MIT License
Classifier: Programming Language :: Python :: 3
Classifier: Programming Language :: Python :: 3.7
Classifier: Programming Language :: Python :: 3.8
Classifier: Programming Language :: Python :: 3.9
Classifier: Programming Language :: Python :: 3.10
Classifier: Programming Language :: Python :: 3.11
Requires-Dist: pysdl2-dll (>=2.26.2,<3.0.0)
